brat_tools/BC2GMtoStandoff.py
brat_tools/BIOtoStandoff.py
brat_tools/MetaMaptoStandoff.py
brat_tools/__init__.py
brat_tools/annalign.py
brat_tools/anncut.py
brat_tools/anneval.py
brat_tools/anntoconll.py
brat_tools/aziitostandoff.py
brat_tools/backup.py
brat_tools/biocontext2standoff.py
brat_tools/bioes2standoff.py
brat_tools/catann.py
brat_tools/checkann.py
brat_tools/colourise.py
brat_tools/conll00tostandoff.py
brat_tools/conll02tostandoff.py
brat_tools/conll09tostandoff.py
brat_tools/conll2standoff.py
brat_tools/conllXtostandoff.py
brat_tools/convert-EntrezGene.py
brat_tools/convert-NCBI-disease.py
brat_tools/convert-NCBITaxon.py
brat_tools/coresctostandoff.py
brat_tools/diff_and_mark.py
brat_tools/discsegtostandoff.py
brat_tools/ent2event.py
brat_tools/fix_annotations.py
brat_tools/generate-static.py
brat_tools/idnorm.py
brat_tools/malt2connlX.py
brat_tools/merge.py
brat_tools/metamaptaggerservice.py
brat_tools/nersuitetaggerservice.py
brat_tools/norm_db_init.py
brat_tools/norm_db_lookup.py
brat_tools/oboextract.py
brat_tools/offlinearize.py
brat_tools/pubdic_tagger.py
brat_tools/randomtaggerservice.py
brat_tools/respace.py
brat_tools/restoataggerservice.py
brat_tools/sentencesplit.py
brat_tools/tokenservice.py
brat_tools/troubleshooting.py
brat_tools/unmerge.py
brat_tools/xmlize.py
brat_tools-0.1.dist-info/METADATA
brat_tools-0.1.dist-info/WHEEL
brat_tools-0.1.dist-info/top_level.txt
brat_tools-0.1.dist-info/RECORD
